gspreader/__init__.py
gspreader/__main__.py
gspreader/config.py
gspreader/gspreader.py
gspreader-0.1.25.dist-info/METADATA
gspreader-0.1.25.dist-info/WHEEL
gspreader-0.1.25.dist-info/RECORD
